MANIFEST.in
README.md
requirements.txt
setup.py
funion/__init__.py
funion/cli.py
funion/combine_contracts.py
funion/combine_contracts_advanced.py
funion/compile_contract.py
funion/utils.py
funion.egg-info/PKG-INFO
funion.egg-info/SOURCES.txt
funion.egg-info/dependency_links.txt
funion.egg-info/entry_points.txt
funion.egg-info/requires.txt
funion.egg-info/top_level.txt