Metadata-Version: 2.1
Name: funion
Version: 0.1.2
Summary: A tool to put all dependent libraries or contracts to a single file for a Solidity smart contract
Home-page: UNKNOWN
Author: isctae
License: MIT
Keywords: Solidity smart contracts
Platform: UNKNOWN
Requires-Python: >=3.6.0
